odoo/addons/analytic_hr_department_restriction/README.rst
odoo/addons/analytic_hr_department_restriction/__init__.py
odoo/addons/analytic_hr_department_restriction/__manifest__.py
odoo/addons/analytic_hr_department_restriction/i18n/analytic_hr_department_restriction.pot
odoo/addons/analytic_hr_department_restriction/i18n/es.po
odoo/addons/analytic_hr_department_restriction/i18n/it.po
odoo/addons/analytic_hr_department_restriction/migrations/18.0.1.0.0/post-migration.py
odoo/addons/analytic_hr_department_restriction/migrations/18.0.1.0.0/pre-migration.py
odoo/addons/analytic_hr_department_restriction/migrations/18.0.1.1.0/post-migration.py
odoo/addons/analytic_hr_department_restriction/models/__init__.py
odoo/addons/analytic_hr_department_restriction/models/account_analytic_account.py
odoo/addons/analytic_hr_department_restriction/models/account_analytic_plan.py
odoo/addons/analytic_hr_department_restriction/models/ir_rule.py
odoo/addons/analytic_hr_department_restriction/readme/CONFIGURE.md
odoo/addons/analytic_hr_department_restriction/readme/CONTRIBUTORS.md
odoo/addons/analytic_hr_department_restriction/readme/DESCRIPTION.md
odoo/addons/analytic_hr_department_restriction/readme/USAGE.md
odoo/addons/analytic_hr_department_restriction/security/groups.xml
odoo/addons/analytic_hr_department_restriction/static/description/icon.png
odoo/addons/analytic_hr_department_restriction/static/description/index.html
odoo/addons/analytic_hr_department_restriction/tests/__init__.py
odoo/addons/analytic_hr_department_restriction/tests/test_analytic_hr_department_restriction.py
odoo/addons/analytic_hr_department_restriction/views/account_analytic_account_views.xml
odoo/addons/analytic_hr_department_restriction/views/account_analytic_plan_views.xml
odoo_addon_analytic_hr_department_restriction-18.0.1.1.0.5.dist-info/METADATA
odoo_addon_analytic_hr_department_restriction-18.0.1.1.0.5.dist-info/WHEEL
odoo_addon_analytic_hr_department_restriction-18.0.1.1.0.5.dist-info/top_level.txt
odoo_addon_analytic_hr_department_restriction-18.0.1.1.0.5.dist-info/RECORD
